pysilpo/__init__.py
pysilpo/client.py
pysilpo/services/__init__.py
pysilpo/services/authorization.py
pysilpo/services/cheque.py
pysilpo/services/product.py
pysilpo/services/store.py
pysilpo/utils/__init__.py
pysilpo/utils/cache.py
pysilpo/utils/cursor.py
pysilpo/utils/enums.py
pysilpo/utils/exceptions.py
pysilpo/utils/utils.py
pysilpo-1.0.2.dist-info/LICENSE
pysilpo-1.0.2.dist-info/METADATA
pysilpo-1.0.2.dist-info/WHEEL
pysilpo-1.0.2.dist-info/top_level.txt
pysilpo-1.0.2.dist-info/RECORD
