Metadata-Version: 2.2
Name: pysilpo
Version: 1.0.2
Summary: UNOFFICIAL API client for Silpo (Ukrainian supermarket chain)
Author: iYasha
License:                                  Apache License
Project-URL: Source, https://github.com/iYasha/pysilpo
Project-URL: Tracker, https://github.com/iYasha/pysilpo/issues
Keywords: pysilpo,silpo,ukraine,supermarket
Classifier: Intended Audience :: Developers
Classifier: License :: OSI Approved :: Apache Software License
Classifier: Operating System :: OS Independent
Classifier: Programming Language :: Python :: 3
Classifier: Programming Language :: Python :: 3 :: Only
Classifier: Programming Language :: Python :: 3.9
Classifier: Programming Language :: Python :: 3.10
Classifier: Programming Language :: Python :: 3.11
Classifier: Programming Language :: Python :: 3.12
Requires-Python: >=3.9
License-File: LICENSE
Requires-Dist: pydantic<3.0,>=2.0
Requires-Dist: PyJWT<3.0,>=2.8
Provides-Extra: docs
Requires-Dist: sphinx>=7; extra == "docs"
